sum_pai/__init__.py
sum_pai/__main__.py
sum_pai/code_extractor.py
sum_pai/constants.py
sum_pai/create_search_embedding.py
sum_pai/file_io.py
sum_pai/loguru_config.py
sum_pai/search_project.py
sum_pai/embedding/__init__.py
sum_pai/embedding/batch.py
sum_pai/embedding/convert.py
sum_pai/embedding/create.py
sum_pai/embedding/length_safe.py
sum_pai/embedding/loading.py
sum_pai/process/__init__.py
sum_pai/process/classes.py
sum_pai/process/code_element.py
sum_pai/process/compare.py
sum_pai/process/directory.py
sum_pai/process/file.py
sum_pai/process/functions.py
sum_pai/process/global_level.py
sum_pai/process/summary_embed.py
sum_pai/search/__init__.py
sum_pai/search/knn.py
sum_pai/search/svm.py
sum_pai/summary/__init__.py
sum_pai/summary/chat_completion.py
sum_pai/summary/code.py
sum_pai/summary/feature.py
sum_pai/summary/text.py
sum_pai-0.4.0.dist-info/METADATA
sum_pai-0.4.0.dist-info/WHEEL
sum_pai-0.4.0.dist-info/entry_points.txt
sum_pai-0.4.0.dist-info/licenses/LICENSE
sum_pai-0.4.0.dist-info/RECORD
