Metadata-Version: 2.1
Name: sum-pai
Version: 0.4.0
Summary: A Python library for cataloging and searching python files.
Project-URL: Homepage, https://github.com/BillSchumacher/SumPAI
Project-URL: Bug Tracker, https://github.com/BillSchumacher/SumPAI
Author-email: Bill Schumacher <34168009+BillSchumacher@users.noreply.github.com>
License-File: LICENSE
Classifier: License :: OSI Approved :: MIT License
Classifier: Operating System :: OS Independent
Classifier: Programming Language :: Python :: 3
Requires-Python: >=3.7
Requires-Dist: black
Requires-Dist: build
Requires-Dist: cityhash
Requires-Dist: click
Requires-Dist: isort
Requires-Dist: loguru
Requires-Dist: numpy
Requires-Dist: openai
Requires-Dist: pytest
Requires-Dist: python-dotenv
Requires-Dist: scikit-learn
Requires-Dist: setuptools
Requires-Dist: tenacity
Requires-Dist: tiktoken
Requires-Dist: twine
Requires-Dist: wheel
